jupyterlab_freeze/__init__.py
jupyterlab_freeze/_version.py
jupyterlab_freeze/labextension/package.json
jupyterlab_freeze/labextension/schemas/jupyterlab_freeze/package.json.orig
jupyterlab_freeze/labextension/schemas/jupyterlab_freeze/plugin.json
jupyterlab_freeze/labextension/static/434.8508b439caf511ea332f.js
jupyterlab_freeze/labextension/static/580.43e9d1ee8f86de88989a.js
jupyterlab_freeze/labextension/static/747.7cb16bcfa4b7cf06bf94.js
jupyterlab_freeze/labextension/static/remoteEntry.cbac5b565de77142913c.js
jupyterlab_freeze/labextension/static/style.js
jupyterlab_freeze/labextension/static/third-party-licenses.json
jupyterlab_freeze-0.1.2.data/data/share/jupyter/labextensions/jupyterlab_freeze/package.json
jupyterlab_freeze-0.1.2.data/data/share/jupyter/labextensions/jupyterlab_freeze/schemas/jupyterlab_freeze/package.json.orig
jupyterlab_freeze-0.1.2.data/data/share/jupyter/labextensions/jupyterlab_freeze/schemas/jupyterlab_freeze/plugin.json
jupyterlab_freeze-0.1.2.data/data/share/jupyter/labextensions/jupyterlab_freeze/static/434.8508b439caf511ea332f.js
jupyterlab_freeze-0.1.2.data/data/share/jupyter/labextensions/jupyterlab_freeze/static/580.43e9d1ee8f86de88989a.js
jupyterlab_freeze-0.1.2.data/data/share/jupyter/labextensions/jupyterlab_freeze/static/747.7cb16bcfa4b7cf06bf94.js
jupyterlab_freeze-0.1.2.data/data/share/jupyter/labextensions/jupyterlab_freeze/static/remoteEntry.cbac5b565de77142913c.js
jupyterlab_freeze-0.1.2.data/data/share/jupyter/labextensions/jupyterlab_freeze/static/style.js
jupyterlab_freeze-0.1.2.data/data/share/jupyter/labextensions/jupyterlab_freeze/static/third-party-licenses.json
jupyterlab_freeze-0.1.2.data/data/share/jupyter/labextensions/jupyterlab_freeze/install.json
jupyterlab_freeze-0.1.2.dist-info/METADATA
jupyterlab_freeze-0.1.2.dist-info/WHEEL
jupyterlab_freeze-0.1.2.dist-info/licenses/LICENSE
jupyterlab_freeze-0.1.2.dist-info/licenses/LICENSE-3rdparty.csv
jupyterlab_freeze-0.1.2.dist-info/licenses/NOTICE
jupyterlab_freeze-0.1.2.dist-info/RECORD
