Metadata-Version: 2.3
Name: jupyterlab_freeze
Version: 0.1.2
Dynamic: Keywords
Summary: Jupyter freeze extension for jupyterlab!
Project-URL: Homepage, https://github.com/DataDog/jupyterlab-freeze
Project-URL: Bug Tracker, https://github.com/DataDog/jupyterlab-freeze/issues
Project-URL: Repository, https://github.com/DataDog/jupyterlab-freeze
Author-email: Carlos Dominguez Becerril <carlos.dominguez@datadoghq.com>
License: BSD 3-Clause License
Classifier: Framework :: Jupyter
Classifier: Framework :: Jupyter :: JupyterLab
Classifier: Framework :: Jupyter :: JupyterLab :: 4
Classifier: Framework :: Jupyter :: JupyterLab :: Extensions
Classifier: Framework :: Jupyter :: JupyterLab :: Extensions :: Prebuilt
Classifier: License :: OSI Approved :: BSD License
Classifier: Programming Language :: Python
Classifier: Programming Language :: Python :: 3
Classifier: Programming Language :: Python :: 3.8
Classifier: Programming Language :: Python :: 3.9
Classifier: Programming Language :: Python :: 3.10
Classifier: Programming Language :: Python :: 3.11
Classifier: Programming Language :: Python :: 3.12
Requires-Python: >=3.8
